certbot_dns_hetzner_cloud/__init__.py
certbot_dns_hetzner_cloud/authenticator.py
certbot_dns_hetzner_cloud/hetzner_cloud_helper.py
certbot_dns_hetzner_cloud-1.0.4.dist-info/licenses/LICENSE.txt
certbot_dns_hetzner_cloud-1.0.4.dist-info/METADATA
certbot_dns_hetzner_cloud-1.0.4.dist-info/WHEEL
certbot_dns_hetzner_cloud-1.0.4.dist-info/entry_points.txt
certbot_dns_hetzner_cloud-1.0.4.dist-info/top_level.txt
certbot_dns_hetzner_cloud-1.0.4.dist-info/RECORD
