Metadata-Version: 2.4
Name: certbot-dns-hetzner-cloud
Version: 1.0.4
Summary: Certbot DNS Plugin for Hetzner Cloud DNS
Author: Rüdiger Olschewsky
License: MIT
Project-URL: Homepage, https://github.com/rolschewsky/certbot-dns-hetzner-cloud
Project-URL: Repository, https://github.com/rolschewsky/certbot-dns-hetzner-cloud
Keywords: certbot,dns,hetzner,acme,letsencrypt
Requires-Python: >=3.10
License-File: LICENSE.txt
Requires-Dist: certbot>=2.0
Requires-Dist: tldextract>=5.3.0
Requires-Dist: hcloud>=2.8.0
Provides-Extra: dev
Requires-Dist: pytest; extra == "dev"
Requires-Dist: pytest-cov; extra == "dev"
Dynamic: license-file
